docs/source/conf.py
flask/example_api_client.py
flask/flask_api.py
naamkaran/__init__.py
naamkaran/generate.py
naamkaran/model.py
naamkaran/naam.py
naamkaran/utils.py
naamkaran/models/naamkaran.pt
naamkaran/models/names_vec.joblib
naamkaran/tests/__init__.py
naamkaran/tests/test_010_gen_names.py
naamkaran/tests/test_020_model.py
naamkaran-0.2.0.dist-info/licenses/LICENSE
naamkaran-0.2.0.dist-info/METADATA
naamkaran-0.2.0.dist-info/WHEEL
naamkaran-0.2.0.dist-info/entry_points.txt
naamkaran-0.2.0.dist-info/top_level.txt
naamkaran-0.2.0.dist-info/RECORD
