Metadata-Version: 2.4
Name: naamkaran
Version: 0.2.0
Summary: Generative model for names.
Author-email: Rajashekar Chintalapati <rajshekar.ch@gmail.com>, Gaurav Sood <gsood07@gmail.com>
License-Expression: MIT
Project-URL: Homepage, https://github.com/appeler/naamkaran
Project-URL: Documentation, https://appeler.github.io/naamkaran/
Project-URL: Repository, https://github.com/appeler/naamkaran
Project-URL: Issues, https://github.com/appeler/naamkaran/issues
Keywords: generate,names,machine-learning,nlp
Classifier: Development Status :: 4 - Beta
Classifier: Intended Audience :: Developers
Classifier: Programming Language :: Python :: 3
Classifier: Programming Language :: Python :: 3.11
Classifier: Programming Language :: Python :: 3.12
Classifier: Programming Language :: Python :: 3.13
Classifier: Topic :: Scientific/Engineering :: Information Analysis
Classifier: Topic :: Software Development :: Libraries :: Python Modules
Classifier: Topic :: Utilities
Requires-Python: >=3.11
License-File: LICENSE
Requires-Dist: torch<3.0.0,>=2.8.0
Requires-Dist: pandas>=2.2.0
Requires-Dist: joblib>=1.4.0
Requires-Dist: scikit-learn>=1.5.0
Provides-Extra: dev
Requires-Dist: pytest>=7.0.0; extra == "dev"
Requires-Dist: pytest-cov; extra == "dev"
Requires-Dist: black; extra == "dev"
Requires-Dist: isort; extra == "dev"
Requires-Dist: flake8; extra == "dev"
Requires-Dist: mypy; extra == "dev"
Requires-Dist: pre-commit; extra == "dev"
Provides-Extra: test
Requires-Dist: pytest>=7.0.0; extra == "test"
Requires-Dist: pytest-cov; extra == "test"
Provides-Extra: web
Requires-Dist: gradio>=3.0.0; extra == "web"
Requires-Dist: flask>=2.0.0; extra == "web"
Dynamic: license-file
